llama_index/llms/openai_like/__init__.py
llama_index/llms/openai_like/base.py
llama_index_llms_openai_like-0.6.0.dist-info/METADATA
llama_index_llms_openai_like-0.6.0.dist-info/WHEEL
llama_index_llms_openai_like-0.6.0.dist-info/licenses/LICENSE
llama_index_llms_openai_like-0.6.0.dist-info/RECORD
