Metadata-Version: 2.4
Name: llama-index-llms-openai-like
Version: 0.6.0
Summary: llama-index llms openai like integration
Author-email: Your Name <you@example.com>
License-Expression: MIT
License-File: LICENSE
Requires-Python: <4.0,>=3.9
Requires-Dist: llama-index-core<0.15,>=0.14.3
Requires-Dist: llama-index-llms-openai<0.7,>=0.6.0
Provides-Extra: transformers
Requires-Dist: transformers<5,>=4.37.0; extra == 'transformers'
